{
  "formatName": "PowerPoint Presentation",
  "version": "1.8",
  "extensions": [
    ".pptx"
  ],
  "description": "Microsoft PowerPoint Open XML presentation",
  "category": "Documents",
  "author": "WPFHexaEditor Team",
  "references": {
    "specifications": [
      "PowerPoint Presentation Format"
    ],
    "WebLinks": [
      "https://en.wikipedia.org/wiki/PPTX"
    ]
  },
  "detection": {
    "signature": "504B0304",
    "offset": 0,
    "required": true,
    "validation": {
      "min_file_size": 4,
      "max_signature_offset": 1024
    }
  },
  "functions": {
    "parseZIPArchive": "Parse Office document as ZIP archive to extract slides",
    "extractUTF8String": "Extract presentation properties (title, author, subject)",
    "readUInt32LE": "Read ZIP header fields (signatures, sizes, CRC)"
  },
  "variables": {
    "currentOffset": 0,
    "fileCount": 0,
    "title": "Unknown",
    "author": "Unknown",
    "subject": "Unknown",
    "slides": 0,
    "notes": 0,
    "layout": "Unknown"
  },
  "blocks": [
    {
      "type": "signature",
      "name": "ZIP Signature",
      "offset": 0,
      "length": 4,
      "color": "#FF6B6B",
      "opacity": 0.4,
      "description": "PPTX is a ZIP container"
    },
    {
      "type": "field",
      "name": "ZIP Header",
      "offset": 4,
      "length": 26,
      "color": "#4ECDC4",
      "opacity": 0.3,
      "description": "ZIP local file header"
    }
  ],
  "mime_types": [
    "application/pptx"
  ],
  "quality_metrics": {
    "completeness_score": 92,
    "documentation_level": "detailed",
    "blocks_defined": 2,
    "validation_rules": 0,
    "last_updated": "2026-02-23",
    "auto_refined": true
  },
  "software": [
    "PDF readers",
    "Office suites"
  ],
  "use_cases": [
    "General file usage",
    "Data storage"
  ],
  "format_relationships": {
    "category": "Documents",
    "extensions": [
      ".pptx"
    ]
  },
  "technical_details": {
    "primary_extension": ".pptx",
    "defined_fields": 2
  },
  "MimeTypes": [
    "application/vnd.openxmlformats-officedocument.presentationml.presentation"
  ],
  "Software": [
    "Microsoft PowerPoint",
    "LibreOffice Impress",
    "Google Slides",
    "Keynote"
  ],
  "UseCases": [
    "Presentations",
    "Slides",
    "Lectures",
    "Business pitches"
  ],
  "QualityMetrics": {
    "CompletenessScore": 78,
    "DocumentationLevel": "detailed",
    "BlocksDefined": 5,
    "ValidationRules": 2,
    "LastUpdated": "2025-01-11",
    "PriorityFormat": true,
    "AutoRefined": false
  },
  "TechnicalDetails": {
    "DocumentFormat": true,
    "Container": "ZIP (Office Open XML)"
  },
  "version_history": {
    "commit_count": 8,
    "change_percentage": 232.77,
    "last_updated": "2026-02-24"
  }
}