{
    "formatName": "Windows Media Video",
    "version": "1.0",
    "extensions": [
        ".wmv",
        ".wma",
        ".asf"
    ],
    "description": "Windows Media Video/Audio format (ASF container)",
    "category": "Video",
    "author": "WPFHexaEditor Team",
    "references": {
        "specifications": [
            "Microsoft AVI RIFF File Format",
            "Audio Video Interleave Format"
        ],
        "web_links": [
            "https://docs.microsoft.com/en-us/windows/win32/directshow/avi-riff-file-reference",
            "https://en.wikipedia.org/wiki/Audio_Video_Interleave"
        ]
    },
    "detection": {
        "signature": "3026B2758E66CF11",
        "offset": 0,
        "required": true
    },
    "variables": {
        "currentOffset": 0
    },
    "blocks": [
        {
            "type": "signature",
            "name": "ASF Header GUID",
            "offset": 0,
            "length": 16,
            "color": "#FF6B6B",
            "opacity": 0.4,
            "description": "Advanced Systems Format header"
        },
        {
            "type": "field",
            "name": "Object Size",
            "offset": 16,
            "length": 8,
            "color": "#4ECDC4",
            "opacity": 0.3,
            "description": "Size of header object"
        }
    ]
}